{"data":{"allMarkdownRemark":{"edges":[{"node":{"fields":{"slug":"/posts/optimisation","categorySlug":"/category/tutorial/"},"frontmatter":{"title":"Optimizing the performance of my personal website","date":"2018-01-24","category":"Tutorial","description":"Incremental changes for a faster first meaningful paint."}}},{"node":{"fields":{"slug":"/posts/star-wars","categorySlug":"/category/tutorial/"},"frontmatter":{"title":"Developing the Star Wars opening crawl in HTML/CSS","date":"2018-01-15","category":"Tutorial","description":"I have a bad feeling about this."}}},{"node":{"fields":{"slug":"/posts/heroku-api","categorySlug":"/category/node/"},"frontmatter":{"title":"Deploying an API to Heroku","date":"2017-12-28","category":"Node","description":"It's free and easy to set up."}}},{"node":{"fields":{"slug":"/posts/intro-electron","categorySlug":"/category/javascript/"},"frontmatter":{"title":"Coding a desktop app with Electron and Angular","date":"2017-12-20","category":"Javascript","description":"Lots of apps you might use on a daily basis use Electron."}}}]}},"pageContext":{"isCreatedByStatefulCreatePages":false,"currentPage":7,"postsLimit":4,"postsOffset":28,"prevPagePath":"/page/6","nextPagePath":"/page/8","hasPrevPage":true,"hasNextPage":true}}